pydnfex/__init__.py
pydnfex/const.py
pydnfex/hard_code.py
pydnfex/img/__init__.py
pydnfex/img/image/__init__.py
pydnfex/img/image/color_board.py
pydnfex/img/image/exception.py
pydnfex/img/image/factory.py
pydnfex/img/image/image.py
pydnfex/img/image/link.py
pydnfex/img/image/sprite.py
pydnfex/img/image/extra/__init__.py
pydnfex/img/image/extra/sprite.py
pydnfex/img/image/extra/zlib.py
pydnfex/img/image/format/__init__.py
pydnfex/img/image/format/color.py
pydnfex/img/image/format/convertor.py
pydnfex/img/image/format/f1555.py
pydnfex/img/image/format/f4444.py
pydnfex/img/image/format/f8888.py
pydnfex/img/image/format/factory.py
pydnfex/img/image/format/format.py
pydnfex/img/version/__init__.py
pydnfex/img/version/factory.py
pydnfex/img/version/img.py
pydnfex/img/version/v1.py
pydnfex/img/version/v2.py
pydnfex/img/version/v4.py
pydnfex/img/version/v5.py
pydnfex/img/version/v6.py
pydnfex/npk/__init__.py
pydnfex/npk/file.py
pydnfex/util/__init__.py
pydnfex/util/common.py
pydnfex/util/image.py
pydnfex/util/io_helper.py
PyDnfEx-0.1.0.dist-info/LICENSE
PyDnfEx-0.1.0.dist-info/METADATA
PyDnfEx-0.1.0.dist-info/WHEEL
PyDnfEx-0.1.0.dist-info/top_level.txt
PyDnfEx-0.1.0.dist-info/RECORD
