Metadata-Version: 2.1
Name: PyDnfEx
Version: 0.1.0
Summary: A data pack extract lib for Dungeon & Fighter.
Home-page: https://github.com/HsOjo/PyDnfEx/
Author: HsOjo
Author-email: hsojo@qq.com
License: UNKNOWN
Keywords: python3 dnf
Platform: UNKNOWN
Classifier: Programming Language :: Python :: 3
Classifier: Operating System :: OS Independent
Classifier: License :: OSI Approved :: GNU General Public License (GPL)
Requires-Python: >=3.7
License-File: LICENSE
Requires-Dist: Pillow
